LICENSE
MANIFEST.in
README.md
pyproject.toml
setup.py
csrc/tensor_ops.cpp
csrc/tensor_ops.h
csrc/cpu/tensor_cpu.cpp
csrc/cuda/cuda_utils.cuh
csrc/cuda/tensor_cuda.cu
csrc/cuda/kernels/elementwise.cu
csrc/cuda/kernels/matmul.cu
csrc/cuda/kernels/reduction.cu
csrc/cuda/kernels/reduction.cuh
tensorax/__init__.py
tensorax/functional.py
tensorax/optim.py
tensorax/tensor.py
tensorax.egg-info/PKG-INFO
tensorax.egg-info/SOURCES.txt
tensorax.egg-info/dependency_links.txt
tensorax.egg-info/requires.txt
tensorax.egg-info/top_level.txt
tensorax/constants/__init__.py
tensorax/constants/devices.py
tensorax/constants/numerical.py
tensorax/nn/__init__.py
tensorax/nn/layers.py
tensorax/nn/module.py
tensorax/utils/shape_utils.py
tensorax/utils/type_checks.py