Metadata-Version: 2.4
Name: tensorax
Version: 0.1.3
Summary: A high-performance tensor library with CUDA acceleration
Home-page: https://github.com/NotShrirang/tensorax
Author: Shrirang Mahajan
Author-email: Shrirang Mahajan <shrirangmahajan123@gmail.com>
License-Expression: MIT
Project-URL: Homepage, https://github.com/NotShrirang/tensorax
Project-URL: Documentation, https://tensorax.readthedocs.io
Project-URL: Repository, https://github.com/NotShrirang/tensorax
Project-URL: Issues, https://github.com/NotShrirang/tensorax/issues
Keywords: tensor,deep-learning,cuda,gpu,machine-learning
Classifier: Development Status :: 3 - Alpha
Classifier: Intended Audience :: Developers
Classifier: Intended Audience :: Science/Research
Classifier: Programming Language :: Python :: 3
Classifier: Programming Language :: C++
Classifier: Topic :: Scientific/Engineering
Requires-Python: >=3.8
License-File: LICENSE
Requires-Dist: pybind11>=2.6.0
Provides-Extra: dev
Requires-Dist: pytest>=6.0.0; extra == "dev"
Requires-Dist: pytest-cov>=2.10.0; extra == "dev"
Requires-Dist: black>=21.0; extra == "dev"
Requires-Dist: flake8>=3.9.0; extra == "dev"
Requires-Dist: mypy>=0.900; extra == "dev"
Requires-Dist: sphinx>=4.0.0; extra == "dev"
Requires-Dist: sphinx-rtd-theme>=0.5.0; extra == "dev"
Dynamic: author
Dynamic: home-page
Dynamic: license-file
Dynamic: provides-extra
Dynamic: requires-dist
Dynamic: requires-python
